{
  "id": 776116413,
  "node_id": "R_kgDOLkKYvQ",
  "name": "qualicharge",
  "full_name": "MTES-MCT/qualicharge",
  "private": false,
  "owner": {
    "login": "MTES-MCT",
    "id": 20193330,
    "node_id": "MDEyOk9yZ2FuaXphdGlvbjIwMTkzMzMw",
    "avatar_url": "https://avatars.githubusercontent.com/u/20193330?v=4",
    "gravatar_id": "",
    "url": "https://api.github.com/users/MTES-MCT",
    "html_url": "https://github.com/MTES-MCT",
    "followers_url": "https://api.github.com/users/MTES-MCT/followers",
    "following_url": "https://api.github.com/users/MTES-MCT/following{/other_user}",
    "gists_url": "https://api.github.com/users/MTES-MCT/gists{/gist_id}",
    "starred_url": "https://api.github.com/users/MTES-MCT/starred{/owner}{/repo}",
    "subscriptions_url": "https://api.github.com/users/MTES-MCT/subscriptions",
    "organizations_url": "https://api.github.com/users/MTES-MCT/orgs",
    "repos_url": "https://api.github.com/users/MTES-MCT/repos",
    "events_url": "https://api.github.com/users/MTES-MCT/events{/privacy}",
    "received_events_url": "https://api.github.com/users/MTES-MCT/received_events",
    "type": "Organization",
    "user_view_type": "public",
    "site_admin": false
  },
  "html_url": "https://github.com/MTES-MCT/qualicharge",
  "description": "Améliorer la qualité globale du service de recharge pour véhicules électriques en analysant les données de supervision.",
  "fork": false,
  "url": "https://api.github.com/repos/MTES-MCT/qualicharge",
  "forks_url": "https://api.github.com/repos/MTES-MCT/qualicharge/forks",
  "keys_url": "https://api.github.com/repos/MTES-MCT/qualicharge/keys{/key_id}",
  "collaborators_url": "https://api.github.com/repos/MTES-MCT/qualicharge/collaborators{/collaborator}",
  "teams_url": "https://api.github.com/repos/MTES-MCT/qualicharge/teams",
  "hooks_url": "https://api.github.com/repos/MTES-MCT/qualicharge/hooks",
  "issue_events_url": "https://api.github.com/repos/MTES-MCT/qualicharge/issues/events{/number}",
  "events_url": "https://api.github.com/repos/MTES-MCT/qualicharge/events",
  "assignees_url": "https://api.github.com/repos/MTES-MCT/qualicharge/assignees{/user}",
  "branches_url": "https://api.github.com/repos/MTES-MCT/qualicharge/branches{/branch}",
  "tags_url": "https://api.github.com/repos/MTES-MCT/qualicharge/tags",
  "blobs_url": "https://api.github.com/repos/MTES-MCT/qualicharge/git/blobs{/sha}",
  "git_tags_url": "https://api.github.com/repos/MTES-MCT/qualicharge/git/tags{/sha}",
  "git_refs_url": "https://api.github.com/repos/MTES-MCT/qualicharge/git/refs{/sha}",
  "trees_url": "https://api.github.com/repos/MTES-MCT/qualicharge/git/trees{/sha}",
  "statuses_url": "https://api.github.com/repos/MTES-MCT/qualicharge/statuses/{sha}",
  "languages_url": "https://api.github.com/repos/MTES-MCT/qualicharge/languages",
  "stargazers_url": "https://api.github.com/repos/MTES-MCT/qualicharge/stargazers",
  "contributors_url": "https://api.github.com/repos/MTES-MCT/qualicharge/contributors",
  "subscribers_url": "https://api.github.com/repos/MTES-MCT/qualicharge/subscribers",
  "subscription_url": "https://api.github.com/repos/MTES-MCT/qualicharge/subscription",
  "commits_url": "https://api.github.com/repos/MTES-MCT/qualicharge/commits{/sha}",
  "git_commits_url": "https://api.github.com/repos/MTES-MCT/qualicharge/git/commits{/sha}",
  "comments_url": "https://api.github.com/repos/MTES-MCT/qualicharge/comments{/number}",
  "issue_comment_url": "https://api.github.com/repos/MTES-MCT/qualicharge/issues/comments{/number}",
  "contents_url": "https://api.github.com/repos/MTES-MCT/qualicharge/contents/{+path}",
  "compare_url": "https://api.github.com/repos/MTES-MCT/qualicharge/compare/{base}...{head}",
  "merges_url": "https://api.github.com/repos/MTES-MCT/qualicharge/merges",
  "archive_url": "https://api.github.com/repos/MTES-MCT/qualicharge/{archive_format}{/ref}",
  "downloads_url": "https://api.github.com/repos/MTES-MCT/qualicharge/downloads",
  "issues_url": "https://api.github.com/repos/MTES-MCT/qualicharge/issues{/number}",
  "pulls_url": "https://api.github.com/repos/MTES-MCT/qualicharge/pulls{/number}",
  "milestones_url": "https://api.github.com/repos/MTES-MCT/qualicharge/milestones{/number}",
  "notifications_url": "https://api.github.com/repos/MTES-MCT/qualicharge/notifications{?since,all,participating}",
  "labels_url": "https://api.github.com/repos/MTES-MCT/qualicharge/labels{/name}",
  "releases_url": "https://api.github.com/repos/MTES-MCT/qualicharge/releases{/id}",
  "deployments_url": "https://api.github.com/repos/MTES-MCT/qualicharge/deployments",
  "created_at": "2024-03-22T18:01:23Z",
  "updated_at": "2026-02-12T16:00:52Z",
  "pushed_at": "2026-02-14T23:51:59Z",
  "git_url": "git://github.com/MTES-MCT/qualicharge.git",
  "ssh_url": "git@github.com:MTES-MCT/qualicharge.git",
  "clone_url": "https://github.com/MTES-MCT/qualicharge.git",
  "svn_url": "https://github.com/MTES-MCT/qualicharge",
  "homepage": "https://fabrique-numerique.gitbook.io/qualicharge",
  "size": 312623,
  "stargazers_count": 6,
  "watchers_count": 6,
  "language": "Python",
  "has_issues": true,
  "has_projects": true,
  "has_downloads": true,
  "has_wiki": true,
  "has_pages": false,
  "has_discussions": false,
  "forks_count": 3,
  "mirror_url": null,
  "archived": false,
  "disabled": false,
  "open_issues_count": 32,
  "license": {
    "key": "mit",
    "name": "MIT License",
    "spdx_id": "MIT",
    "url": "https://api.github.com/licenses/mit",
    "node_id": "MDc6TGljZW5zZTEz"
  },
  "allow_forking": true,
  "is_template": false,
  "web_commit_signoff_required": false,
  "has_pull_requests": true,
  "pull_request_creation_policy": "all",
  "topics": [
    "evse",
    "open-data"
  ],
  "visibility": "public",
  "forks": 3,
  "open_issues": 32,
  "watchers": 6,
  "default_branch": "main",
  "permissions": {
    "admin": false,
    "maintain": false,
    "push": false,
    "triage": false,
    "pull": false
  },
  "temp_clone_token": "",
  "custom_properties": {

  },
  "organization": {
    "login": "MTES-MCT",
    "id": 20193330,
    "node_id": "MDEyOk9yZ2FuaXphdGlvbjIwMTkzMzMw",
    "avatar_url": "https://avatars.githubusercontent.com/u/20193330?v=4",
    "gravatar_id": "",
    "url": "https://api.github.com/users/MTES-MCT",
    "html_url": "https://github.com/MTES-MCT",
    "followers_url": "https://api.github.com/users/MTES-MCT/followers",
    "following_url": "https://api.github.com/users/MTES-MCT/following{/other_user}",
    "gists_url": "https://api.github.com/users/MTES-MCT/gists{/gist_id}",
    "starred_url": "https://api.github.com/users/MTES-MCT/starred{/owner}{/repo}",
    "subscriptions_url": "https://api.github.com/users/MTES-MCT/subscriptions",
    "organizations_url": "https://api.github.com/users/MTES-MCT/orgs",
    "repos_url": "https://api.github.com/users/MTES-MCT/repos",
    "events_url": "https://api.github.com/users/MTES-MCT/events{/privacy}",
    "received_events_url": "https://api.github.com/users/MTES-MCT/received_events",
    "type": "Organization",
    "user_view_type": "public",
    "site_admin": false
  },
  "network_count": 3,
  "subscribers_count": 1
}
