{
  "url": "https://github.com/betagouv/awesome-betagouv",
  "name": "awesome-betagouv",
  "description": "Une collection organisée d'outils et de ressources open source de la communauté beta.gouv.fr, conçus pour aider les équipes à construire des services publics numériques de qualité.",
  "language": null,
  "features": [
    "Documentation",
    "Templates de projets",
    "Outils pour le développement produit",
    "Outils data",
    "Ressources communautaires"
  ],
  "audience": "Professionnels",
  "dependencies": [
    "React",
    "Vue.js",
    "Django",
    "Rails",
    "Keycloak",
    "Node.js",
    "Puppeteer",
    "ClamAV"
  ],
  "components": [
    "Frontend React",
    "Frontend Vue.js",
    "Backend Django",
    "Backend Rails",
    "API",
    "Documentation"
  ],
  "auth": {
    "methods": [
      "oauth2"
    ],
    "providers": []
  },
  "tests": null,
  "workflows": null,
  "lastActivity": "2026-01-30T17:16:33+01:00",
  "status": "active",
  "license": null,
  "hasDocumentation": true,
  "metrics": {
    "stars": 14,
    "forks": 3,
    "contributors": null,
    "openIssues": 0
  },
  "tags": [
    "open source",
    "gouvernement",
    "services publics",
    "beta.gouv.fr",
    "outils",
    "ressources"
  ]
}
