{
  "url": "https://github.com/betagouv/acces-cible",
  "name": "acces-cible",
  "description": "Application permettant de contrôler l'accessibilité des sites Internet, et les obligations légales liées à celle-ci.",
  "language": "Ruby",
  "features": [
    "Vérification de l'accessibilité",
    "Analyse du schéma pluriannuel",
    "Gestion des sites web",
    "Gestion des tags",
    "Gestion des utilisateurs",
    "Export CSV"
  ],
  "audience": "Agents de l'Administration",
  "dependencies": [
    "Rails",
    "RSpec",
    "Cucumber",
    "PostgreSQL",
    "SolidQueue",
    "Factory Bot",
    "Axe-core",
    "Ferrum"
  ],
  "components": [
    "Frontend Rails",
    "API REST",
    "Base de données PostgreSQL",
    "Workers SolidQueue"
  ],
  "auth": {
    "methods": [
      "email-password",
      "oauth2"
    ],
    "providers": [
      "ProConnect"
    ]
  },
  "tests": [
    "RSpec",
    "Cucumber"
  ],
  "workflows": [
    "ci.yml"
  ],
  "lastActivity": "2026-01-28T14:44:41+01:00",
  "status": "active",
  "license": "MIT",
  "hasDocumentation": true,
  "metrics": {
    "stars": 5,
    "forks": 3,
    "contributors": null,
    "openIssues": 27
  },
  "tags": [
    "accessibilité",
    "web",
    "conformité",
    "outil",
    "test"
  ]
}
