{
  "url": "https://github.com/betagouv/dsfr-doc",
  "name": "dsfr-doc",
  "description": "Documentation non-officielle du DSFR (Système de Design de l’État Français). Ce projet expose du contenu déjà public mais difficilement accessible.",
  "language": "Pug",
  "features": [],
  "audience": "Professionnels",
  "dependencies": [
    "Pug",
    "http-server"
  ],
  "components": [
    "Frontend (Pug)"
  ],
  "auth": {
    "methods": [
      "none"
    ]
  },
  "tests": null,
  "workflows": [
    "ci.yml"
  ],
  "lastActivity": "2024-12-10T09:18:37Z",
  "status": "active",
  "license": "MIT",
  "hasDocumentation": true,
  "metrics": {
    "stars": 0,
    "forks": 0,
    "contributors": null,
    "openIssues": 0
  },
  "tags": [
    "DSFR",
    "Design System"
  ]
}
