{
  "url": "https://github.com/socialgouv/.github",
  "name": ".github",
  "description": "Ce dépôt contient les fichiers de configuration communautaires par défaut pour l'organisation @SocialGouv sur GitHub. Il fournit des modèles et des outils pour la gestion des workflows et l'automatisation des tâches.",
  "language": "Dhall",
  "features": [],
  "audience": "Agents de l'Administration",
  "dependencies": [
    "prettier",
    "dhall-lang"
  ],
  "components": [
    "Workflows GitHub Actions",
    "Fichiers de configuration Dhall",
    "Scripts Makefile",
    "Automatisation CI/CD"
  ],
  "auth": {
    "methods": [
      "none"
    ]
  },
  "tests": [],
  "workflows": [
    "boto.yml",
    "@workflows-src.yaml"
  ],
  "lastActivity": "2025-11-28T11:39:51Z",
  "status": "active",
  "license": "Apache-2.0",
  "hasDocumentation": true,
  "metrics": {
    "stars": 2,
    "forks": 1,
    "contributors": null,
    "openIssues": 11
  },
  "tags": [
    "github",
    "automation",
    "ci/cd",
    "dhall",
    "github actions",
    "configuration"
  ]
}
