{
  "url": "https://github.com/incubateur-ademe/bilansclimatsimplifies-backend",
  "name": "bilansclimatsimplifies-backend",
  "description": "Ce projet est un backend pour la simplification des bilans climats. Il fournit une API pour gérer les données d'émissions et les rapports associés. Il est conçu pour faciliter l'analyse et la visualisation des données climatiques.",
  "language": "Python",
  "features": [
    "Gestion des données d'émissions",
    "Génération de rapports",
    "Export de données",
    "Authentification utilisateur"
  ],
  "audience": "Professionnels",
  "dependencies": [
    "Django",
    "djangorestframework",
    "psycopg2",
    "djangorestframework-simplejwt",
    "openpyxl"
  ],
  "components": [
    "API REST",
    "Base de données PostgreSQL",
    "Backend Django"
  ],
  "auth": {
    "methods": [
      "oauth2",
      "jwt"
    ],
    "providers": []
  },
  "tests": [
    "Pytest"
  ],
  "workflows": [
    "codeql-analysis.yml",
    "django.yml"
  ],
  "lastActivity": "2024-03-07T20:19:51Z",
  "status": "active",
  "license": "MIT",
  "hasDocumentation": true,
  "metrics": {
    "stars": 2,
    "forks": 1,
    "contributors": null,
    "openIssues": 12
  },
  "tags": [
    "Python",
    "Django",
    "API",
    "Emissions",
    "Climat",
    "Rapports"
  ]
}
