{
  "url": "https://github.com/socialgouv/redis-commander-scalingo",
  "name": "redis-commander-scalingo",
  "description": "Outil de gestion web pour Redis écrit en node.js. Permet de visualiser et d'éditer les données stockées dans plusieurs serveurs Redis.",
  "language": "JavaScript",
  "features": [
    "Gestion de chaînes de caractères",
    "Gestion de listes",
    "Gestion d'ensembles",
    "Gestion d'ensembles triés",
    "Support basique des Streams",
    "Support basique des documents ReJSON"
  ],
  "audience": "Professionnels",
  "dependencies": [
    "Node.js",
    "ioredis",
    "express",
    "bcryptjs"
  ],
  "components": [
    "Frontend web (HTML, CSS, JavaScript)",
    "API REST (Express.js)",
    "Interface utilisateur (jQuery, Bootstrap)",
    "Connexion à Redis (ioredis)"
  ],
  "auth": {
    "methods": [
      "email-password",
      "session"
    ]
  },
  "tests": null,
  "workflows": [
    "chart-test"
  ],
  "lastActivity": "2024-06-05T08:46:13Z",
  "status": "active",
  "license": "MIT",
  "hasDocumentation": true,
  "metrics": {
    "stars": 0,
    "forks": 0,
    "contributors": 0,
    "openIssues": 0
  },
  "tags": [
    "redis",
    "management",
    "web interface",
    "node.js",
    "database"
  ]
}
