{
  "id": 279289686,
  "node_id": "MDEwOlJlcG9zaXRvcnkyNzkyODk2ODY=",
  "name": "tchatcha",
  "full_name": "etalab/tchatcha",
  "private": false,
  "owner": {
    "login": "etalab",
    "id": 5313610,
    "node_id": "MDEyOk9yZ2FuaXphdGlvbjUzMTM2MTA=",
    "avatar_url": "https://avatars.githubusercontent.com/u/5313610?v=4",
    "gravatar_id": "",
    "url": "https://api.github.com/users/etalab",
    "html_url": "https://github.com/etalab",
    "followers_url": "https://api.github.com/users/etalab/followers",
    "following_url": "https://api.github.com/users/etalab/following{/other_user}",
    "gists_url": "https://api.github.com/users/etalab/gists{/gist_id}",
    "starred_url": "https://api.github.com/users/etalab/starred{/owner}{/repo}",
    "subscriptions_url": "https://api.github.com/users/etalab/subscriptions",
    "organizations_url": "https://api.github.com/users/etalab/orgs",
    "repos_url": "https://api.github.com/users/etalab/repos",
    "events_url": "https://api.github.com/users/etalab/events{/privacy}",
    "received_events_url": "https://api.github.com/users/etalab/received_events",
    "type": "Organization",
    "user_view_type": "public",
    "site_admin": false
  },
  "html_url": "https://github.com/etalab/tchatcha",
  "description": "Captchacha: solution de vérification de formulaire",
  "fork": false,
  "url": "https://api.github.com/repos/etalab/tchatcha",
  "forks_url": "https://api.github.com/repos/etalab/tchatcha/forks",
  "keys_url": "https://api.github.com/repos/etalab/tchatcha/keys{/key_id}",
  "collaborators_url": "https://api.github.com/repos/etalab/tchatcha/collaborators{/collaborator}",
  "teams_url": "https://api.github.com/repos/etalab/tchatcha/teams",
  "hooks_url": "https://api.github.com/repos/etalab/tchatcha/hooks",
  "issue_events_url": "https://api.github.com/repos/etalab/tchatcha/issues/events{/number}",
  "events_url": "https://api.github.com/repos/etalab/tchatcha/events",
  "assignees_url": "https://api.github.com/repos/etalab/tchatcha/assignees{/user}",
  "branches_url": "https://api.github.com/repos/etalab/tchatcha/branches{/branch}",
  "tags_url": "https://api.github.com/repos/etalab/tchatcha/tags",
  "blobs_url": "https://api.github.com/repos/etalab/tchatcha/git/blobs{/sha}",
  "git_tags_url": "https://api.github.com/repos/etalab/tchatcha/git/tags{/sha}",
  "git_refs_url": "https://api.github.com/repos/etalab/tchatcha/git/refs{/sha}",
  "trees_url": "https://api.github.com/repos/etalab/tchatcha/git/trees{/sha}",
  "statuses_url": "https://api.github.com/repos/etalab/tchatcha/statuses/{sha}",
  "languages_url": "https://api.github.com/repos/etalab/tchatcha/languages",
  "stargazers_url": "https://api.github.com/repos/etalab/tchatcha/stargazers",
  "contributors_url": "https://api.github.com/repos/etalab/tchatcha/contributors",
  "subscribers_url": "https://api.github.com/repos/etalab/tchatcha/subscribers",
  "subscription_url": "https://api.github.com/repos/etalab/tchatcha/subscription",
  "commits_url": "https://api.github.com/repos/etalab/tchatcha/commits{/sha}",
  "git_commits_url": "https://api.github.com/repos/etalab/tchatcha/git/commits{/sha}",
  "comments_url": "https://api.github.com/repos/etalab/tchatcha/comments{/number}",
  "issue_comment_url": "https://api.github.com/repos/etalab/tchatcha/issues/comments{/number}",
  "contents_url": "https://api.github.com/repos/etalab/tchatcha/contents/{+path}",
  "compare_url": "https://api.github.com/repos/etalab/tchatcha/compare/{base}...{head}",
  "merges_url": "https://api.github.com/repos/etalab/tchatcha/merges",
  "archive_url": "https://api.github.com/repos/etalab/tchatcha/{archive_format}{/ref}",
  "downloads_url": "https://api.github.com/repos/etalab/tchatcha/downloads",
  "issues_url": "https://api.github.com/repos/etalab/tchatcha/issues{/number}",
  "pulls_url": "https://api.github.com/repos/etalab/tchatcha/pulls{/number}",
  "milestones_url": "https://api.github.com/repos/etalab/tchatcha/milestones{/number}",
  "notifications_url": "https://api.github.com/repos/etalab/tchatcha/notifications{?since,all,participating}",
  "labels_url": "https://api.github.com/repos/etalab/tchatcha/labels{/name}",
  "releases_url": "https://api.github.com/repos/etalab/tchatcha/releases{/id}",
  "deployments_url": "https://api.github.com/repos/etalab/tchatcha/deployments",
  "created_at": "2020-07-13T11:56:41Z",
  "updated_at": "2024-09-15T19:24:56Z",
  "pushed_at": "2021-03-15T18:21:35Z",
  "git_url": "git://github.com/etalab/tchatcha.git",
  "ssh_url": "git@github.com:etalab/tchatcha.git",
  "clone_url": "https://github.com/etalab/tchatcha.git",
  "svn_url": "https://github.com/etalab/tchatcha",
  "homepage": "",
  "size": 174,
  "stargazers_count": 8,
  "watchers_count": 8,
  "language": "CSS",
  "has_issues": true,
  "has_projects": true,
  "has_downloads": true,
  "has_wiki": true,
  "has_pages": false,
  "has_discussions": false,
  "forks_count": 15,
  "mirror_url": null,
  "archived": false,
  "disabled": false,
  "open_issues_count": 1,
  "license": {
    "key": "apache-2.0",
    "name": "Apache License 2.0",
    "spdx_id": "Apache-2.0",
    "url": "https://api.github.com/licenses/apache-2.0",
    "node_id": "MDc6TGljZW5zZTI="
  },
  "allow_forking": true,
  "is_template": false,
  "web_commit_signoff_required": false,
  "topics": [

  ],
  "visibility": "public",
  "forks": 15,
  "open_issues": 1,
  "watchers": 8,
  "default_branch": "master",
  "permissions": {
    "admin": false,
    "maintain": false,
    "push": false,
    "triage": false,
    "pull": false
  },
  "temp_clone_token": "",
  "custom_properties": {

  },
  "organization": {
    "login": "etalab",
    "id": 5313610,
    "node_id": "MDEyOk9yZ2FuaXphdGlvbjUzMTM2MTA=",
    "avatar_url": "https://avatars.githubusercontent.com/u/5313610?v=4",
    "gravatar_id": "",
    "url": "https://api.github.com/users/etalab",
    "html_url": "https://github.com/etalab",
    "followers_url": "https://api.github.com/users/etalab/followers",
    "following_url": "https://api.github.com/users/etalab/following{/other_user}",
    "gists_url": "https://api.github.com/users/etalab/gists{/gist_id}",
    "starred_url": "https://api.github.com/users/etalab/starred{/owner}{/repo}",
    "subscriptions_url": "https://api.github.com/users/etalab/subscriptions",
    "organizations_url": "https://api.github.com/users/etalab/orgs",
    "repos_url": "https://api.github.com/users/etalab/repos",
    "events_url": "https://api.github.com/users/etalab/events{/privacy}",
    "received_events_url": "https://api.github.com/users/etalab/received_events",
    "type": "Organization",
    "user_view_type": "public",
    "site_admin": false
  },
  "network_count": 15,
  "subscribers_count": 1
}
