{
  "url": "https://github.com/betagouv/github-export",
  "name": "github-export",
  "description": "Ce projet permet de migrer des dépôts d'organisations GitHub vers Codeberg, en conservant l'historique complet, les branches, les issues, les pull requests et plus encore. Il offre une solution pour exporter et synchroniser des projets GitHub vers une plateforme alternative.",
  "language": "TypeScript",
  "features": [
    "Migration complète des dépôts",
    "Migration des issues, pull requests, labels, milestones, releases et wikis",
    "Migrations résumables avec suivi de l'état",
    "Traitement par lots pour les grandes organisations",
    "Nouvelles tentatives automatiques avec classification des erreurs"
  ],
  "audience": "Professionnels",
  "dependencies": [
    "@octokit/rest",
    "p-retry",
    "simple-git",
    "zod"
  ],
  "components": [
    "API REST",
    "Client GitHub",
    "Client Codeberg",
    "Orchestration de la migration",
    "Gestion de l'état de la migration"
  ],
  "auth": {
    "methods": [
      "api-key"
    ]
  },
  "tests": null,
  "workflows": [
    "cleanup-inactive-codeberg.yml",
    "migrate-batch.yml",
    "sync-orchestrator.yml"
  ],
  "lastActivity": "2026-01-25T22:11:55Z",
  "status": "active",
  "license": "MIT",
  "hasDocumentation": true,
  "metrics": {
    "stars": 2,
    "forks": 0,
    "contributors": 1,
    "openIssues": 0
  },
  "tags": [
    "github",
    "codeberg",
    "migration",
    "typescript",
    "automation"
  ]
}
