{
  "url": "https://github.com/etalab/schema-generic-template",
  "name": "schema-generic-template",
  "description": "Ce dépôt contient un modèle de départ pour la création d'un schéma générique référençable sur schema.data.gouv.fr. Il permet de décrire un schéma non supporté nativement par la plateforme et de pointer vers une documentation externe.",
  "language": null,
  "features": [],
  "audience": "Professionnels",
  "dependencies": [],
  "components": [
    "Schéma YAML"
  ],
  "auth": {
    "methods": [
      "none"
    ]
  },
  "tests": null,
  "workflows": null,
  "lastActivity": "2023-01-10T17:59:19Z",
  "status": "active",
  "license": "other",
  "hasDocumentation": true,
  "metrics": {
    "stars": 2,
    "forks": 1,
    "contributors": null,
    "openIssues": 0
  },
  "tags": [
    "schéma",
    "YAML",
    "schema.data.gouv.fr",
    "template"
  ]
}
