{
  "url": "https://github.com/etalab/admin_api_entreprise",
  "name": "admin_api_entreprise",
  "description": "Site vitrine / backoffice de l'API Entreprise. Permet de gérer et visualiser les informations relatives à l'API.",
  "language": "Ruby",
  "features": [
    "Gestion des webhooks DataPass",
    "Documentation",
    "Gestion des utilisateurs",
    "Visualisation des données",
    "Authentification",
    "Administration"
  ],
  "audience": "Agents de l'Administration",
  "dependencies": [
    "Ruby",
    "PostgreSQL",
    "Redis",
    "Rails"
  ],
  "components": [
    "Frontend Ruby on Rails",
    "Base de données PostgreSQL",
    "Serveur Redis"
  ],
  "auth": {
    "methods": [
      "email-password"
    ],
    "providers": []
  },
  "tests": [
    "RSpec",
    "Guard"
  ],
  "workflows": [
    "ci_cd.yml",
    "https-deploy-production.yaml",
    "https-deploy-sandbox.yaml",
    "https-deploy-staging.yaml"
  ],
  "lastActivity": "2026-01-30T13:47:47Z",
  "status": "active",
  "license": "MIT",
  "hasDocumentation": true,
  "metrics": {
    "stars": 12,
    "forks": 7,
    "contributors": null,
    "openIssues": 9
  },
  "tags": [
    "API",
    "Rails",
    "Ruby",
    "Administration",
    "FranceConnect",
    "SIADE"
  ]
}
