{
  "url": "https://github.com/mtes-mct/vigieau",
  "name": "vigieau",
  "description": "VigiEau est un monorepo contenant les applications VigiEau et VigiEau Admin. Il permet de gérer et de visualiser les données relatives à l'eau.",
  "language": "TypeScript",
  "features": [
    "Gestion des arrêtés",
    "Visualisation de données",
    "Cartographie",
    "Gestion des utilisateurs",
    "Alertes et notifications",
    "Suivi des restrictions d'eau"
  ],
  "audience": "Agents de l'Administration",
  "dependencies": [
    "NestJS",
    "React",
    "TypeORM",
    "Nuxt.js",
    "Chart.js",
    "Maplibre GL",
    "Passport",
    "Sass"
  ],
  "components": [
    "Backend NestJS",
    "Frontend React (Nuxt.js)",
    "Base de données PostgreSQL",
    "API REST",
    "Interface d'administration",
    "Cartographie interactive"
  ],
  "auth": {
    "methods": [
      "email-password",
      "oauth2",
      "jwt",
      "session"
    ],
    "providers": []
  },
  "tests": [
    "Jest",
    "Cypress",
    "NYC"
  ],
  "workflows": [
    "build",
    "e2e-tests"
  ],
  "lastActivity": "2025-09-30T09:22:11Z",
  "status": "active",
  "license": null,
  "hasDocumentation": true,
  "metrics": {
    "stars": 0,
    "forks": 0,
    "contributors": null,
    "openIssues": 3
  },
  "tags": [
    "eau",
    "environnement",
    "gestion de l'eau",
    "restrictions d'eau",
    "cartographie",
    "administration",
    "NestJS",
    "React",
    "TypeScript"
  ]
}
