{
  "url": "https://github.com/socialgouv/nuxt-dsfr-toaster-module",
  "name": "nuxt-dsfr-toaster-module",
  "description": "Ce module Nuxt Dsfr Toaster permet d'afficher des alertes. Il offre des fonctionnalités comme la limitation de durée des alertes, la gestion du nombre maximal d'alertes à l'écran et l'utilisation du composant DsfrAlert.",
  "language": "JavaScript",
  "features": [
    "Affichage d'alertes",
    "Gestion de la durée des alertes",
    "Limitation du nombre d'alertes",
    "Compatibilité Dsfr"
  ],
  "audience": "Professionnels",
  "dependencies": [
    "@gouvfr/dsfr",
    "@gouvminint/vue-dsfr",
    "@nuxt/kit",
    "defu"
  ],
  "components": [
    "Frontend Vue.js",
    "Module Nuxt",
    "Composables",
    "Plugins"
  ],
  "auth": {
    "methods": [
      "none"
    ]
  },
  "tests": [
    "Vitest"
  ],
  "workflows": [
    "release"
  ],
  "lastActivity": "2025-11-27T04:31:26Z",
  "status": "active",
  "license": "Apache-2.0",
  "hasDocumentation": true,
  "metrics": {
    "stars": 2,
    "forks": 0,
    "contributors": null,
    "openIssues": 12
  },
  "tags": [
    "Nuxt",
    "DSFR",
    "Toaster",
    "Alertes",
    "Module"
  ]
}
