{
  "url": "https://github.com/betagouv/anssi-nis2",
  "name": "anssi-nis2",
  "description": "Accompagne les organisations dans la compréhension et la mise en conformité à NIS 2. Ce projet fournit des outils et des informations pour aider les entités à se préparer et à se conformer à la directive NIS 2.",
  "language": "TypeScript",
  "features": [
    "Simulateur de conformité NIS 2",
    "Informations sur la directive NIS 2",
    "Aide à la préparation",
    "Gestion des emails",
    "Analyse de l'éligibilité"
  ],
  "audience": "Professionnels",
  "dependencies": [
    "Express",
    "PostgreSQL",
    "Papaparse",
    "Axios",
    "@sentry/node",
    "@sentry/react",
    "@codegouvfr/react-dsfr",
    "react",
    "react-dom",
    "react-router-dom"
  ],
  "components": [
    "Frontend React",
    "API REST (Express)",
    "Base de données PostgreSQL",
    "Microservices",
    "Workspaces (anssi-nis2-api, anssi-nis2-ui, commun/core)"
  ],
  "auth": {
    "methods": [
      "none"
    ]
  },
  "tests": [
    "Jest",
    "Vitest",
    "Cypress (inferred from UI tests)"
  ],
  "workflows": [
    "checkov.yml",
    "deploiement.yml",
    "node.js.yml"
  ],
  "lastActivity": "2025-12-19T09:57:29+01:00",
  "status": "active",
  "license": "Apache-2.0",
  "hasDocumentation": true,
  "metrics": {
    "stars": 17,
    "forks": 5,
    "contributors": null,
    "openIssues": 2
  },
  "tags": [
    "cyber-security",
    "france",
    "nis2",
    "typescript",
    "react",
    "postgresql"
  ]
}
